{"cameraMode":{"drawMode":0,"name":"Shaded","section":"Shading Mode"},"sceneLighting":true,"audioPlay":false,"sceneViewState":{"showFog":true,"showMaterialUpdate":false,"showSkybox":true,"showFlares":true,"showImageEffects":true,"showParticleSystems":true},"in2DMode":false,"pivot":{"x":-2.890099287033081,"y":-0.1339879035949707,"z":0.860266923904419},"rotation":{"x":-0.06616131216287613,"y":0.8715257048606873,"z":-0.12264768034219742,"w":-0.4701350927352905},"size":3.5094637870788576,"orthographic":false}